tests
pyqcy
