Metadata-Version: 1.1
Name: pyqcy
Version: 0.4.2
Summary: QuickCheck-like testing framework for Python
Home-page: http://xion.io/pyqcy
Author: Karol Kuczmarski "Xion"
Author-email: karol.kuczmarski@gmail.com
License: Simplified BSD
Platform: any
Classifier: Development Status :: 3 - Alpha
Classifier: Intended Audience :: Developers
Classifier: License :: OSI Approved :: BSD License
Classifier: Operating System :: OS Independent
Classifier: Programming Language :: Python
Classifier: Programming Language :: Python :: 2.6
Classifier: Programming Language :: Python :: 2.7
Classifier: Topic :: Software Development :: Testing
